{"post": {"summary": "Expand all server side generated files and adapt the _service file.", "description": "This command executes the following steps:\n- Expand all server side generated files. Those are the files created by the services, starting with `_service:`.\n- Modify The `_service` file:\n  - Preserve all those services which have the `mode` attribute set to `buildtime`.\n  - Remove the `_service` file only if there aren't any services with the `mode` attribute set to `buildtime`.\n\nAn example of a `_service` file, before:\n  ```\n  <services>\n    <service name=\"obs_scm\">\n      <param name=\"versionformat\">2.11~alpha.%ci.%h</param>\n      <param name=\"url\">https://github.com/openSUSE/open-build-service.git</param>\n      <param name=\"scm\">git</param>\n      <param name=\"revision\">master</param>\n      <param name=\"extract\">dist/obs-server.spec</param>\n    </service>\n    <service name=\"tar\" mode=\"buildtime\"/>\n    <service name=\"recompress\" mode=\"buildtime\">\n      <param name=\"compression\">xz</param>\n      <param name=\"file\">*.tar</param>\n    </service>\n  </services>\n  ```\n\nAn example of a `_service` file, after this command is run:\n  ```\n  <services>\n    <service name=\"tar\" mode=\"buildtime\"/>\n    <service name=\"recompress\" mode=\"buildtime\">\n      <param name=\"compression\">xz</param>\n      <param name=\"file\">*.tar</param>\n    </service>\n  </services>\n  ```\n", "security": [{"basic_authentication": []}], "parameters": [{"$ref: "../components/parameters/project_name.json"}, {"$ref": "../components/package_name.json"}, {"in": "query", "name": "comment", "schema": {"type": "string"}, "description": "Set a comment.", "example": "Merge services."}], "responses": {"200": {"description": "Revision of the merge of the service file.", "content": {"application/xml; charset=utf-8": {"schema": {"$ref": "../components/schemas/revision.json"}, "example": {"rev": 8, "vrev": 8, "srcmd5": "beb268dc9f786efaa585ac07e17fea47", "version": "2.10~pre", "time": 1665060711, "user": "Admin", "comment": null, "requestid": null}}}}, "400": {"description": "Bad Request.\n\nXML Schema used for body validation: [status.xsd](../schema/status.xsd)\n", "content": {"application/xml; charset=utf-8": {"schema": {"$ref": "../components/schemas/api_response.json"}, "examples": {"Package Without _service file": {"value": {"code": 400, "origin": "backend", "summary": "package has no service"}}, "Services Running": {"value": {"code": 400, "origin": "backend", "summary": "service in progress"}}}}}}, "401": {"$ref": "../components/responses/unauthorized.json"}, "403": {"description": "Forbidden.", "content": {"application/xml; charset=utf-8": {"schema": {"$ref": "../components/schemas/api_response.json"}, "example": {"code": "cmd_execution_no_permission", "summary": "no permission to modify package test in project home:Admin"}}}}, "404": {"$ref": "../components/responses/unknown_project_or_package.json"}}, "tags": ["Sources - Packages"]}}
